
{
    "offchainInfo": {
      "name": "Og Node Sale",
      "tokenName": "OG",
      "saleTokenDecimals": 0,
      "preSaleStartDate": "2024-04-16T01:38:36.905Z",
      "allocations": [
        { "name": "Presale", "value": 45 },
        { "name": "Unlocked", "value": 13 },
        { "name": "Locked", "value": 1.5 },
        { "name": "Liquidity", "value": 40 },
        { "name": "Fees", "value": 0.5 }
      ],
      "info": {
        "totalSupply": 10000000000,
        "networkDetails": "Og is the largest modular data layer for gaming, AI, and ∞, pioneering a future where data generates value for all. $20M from Temasek’s Vertex, ConsenSys (Metamask), OKX, HashKey, and more.",
        "liquidityLock": "60% ETH raised",
        "duration": "11 Months",
        "public": "One to anyone",
        "totalRaise": "500 ETH",
        "maxSpendPerAccount": "1.6728 ETH",
        "presalePrice": 33333333,
        "listingPrice": 33333333
      },
      "tokenTradeDate": "2024-04-21T01:38:36.905Z",
      "whitepaperUrl": "https://docs.carv.io/",
      "applicationUrl": "https://carv.io/",
      "programId": "FUiJ7z7iHZyzqRF3rwtHBvUB1VLgBHRTRhutErZRGS8P",
      "accountAddress": "DQgtJsV5EzDYpk4qibBS8rpPyUj9Jx4qe5BvN97sWpfr",
      "rpcUrl": "https://api.devnet.solana.com"
    },
    "onchainInfo": {
      "price": 0.1,
      "priceUnit": "SOL"
    }
  }
